stackdriver_log_formatter/__init__.py
stackdriver_log_formatter/formatter.py
stackdriver_log_formatter/serializer.py
stackdriver_log_formatter-0.1.2.dist-info/LICENSE
stackdriver_log_formatter-0.1.2.dist-info/WHEEL
stackdriver_log_formatter-0.1.2.dist-info/METADATA
stackdriver_log_formatter-0.1.2.dist-info/RECORD
